odoo/addons/ssi_toll_manufacturing/README.rst
odoo/addons/ssi_toll_manufacturing/__init__.py
odoo/addons/ssi_toll_manufacturing/__manifest__.py
odoo/addons/ssi_toll_manufacturing/menu.xml
odoo/addons/ssi_toll_manufacturing/approval_template/batch_toll_manufacturing_acceptance.xml
odoo/addons/ssi_toll_manufacturing/approval_template/batch_toll_manufacturing_order.xml
odoo/addons/ssi_toll_manufacturing/approval_template/toll_manufacturing_acceptance.xml
odoo/addons/ssi_toll_manufacturing/approval_template/toll_manufacturing_order.xml
odoo/addons/ssi_toll_manufacturing/demo/product_category.xml
odoo/addons/ssi_toll_manufacturing/demo/product_product.xml
odoo/addons/ssi_toll_manufacturing/demo/toll_manufacturing_order_type.xml
odoo/addons/ssi_toll_manufacturing/i18n/ssi_toll_manufacturing.pot
odoo/addons/ssi_toll_manufacturing/ir_sequence/batch_toll_manufacturing_acceptance.xml
odoo/addons/ssi_toll_manufacturing/ir_sequence/batch_toll_manufacturing_order.xml
odoo/addons/ssi_toll_manufacturing/ir_sequence/toll_manufacturing_acceptance.xml
odoo/addons/ssi_toll_manufacturing/ir_sequence/toll_manufacturing_order.xml
odoo/addons/ssi_toll_manufacturing/models/__init__.py
odoo/addons/ssi_toll_manufacturing/models/batch_toll_manufacturing_acceptance.py
odoo/addons/ssi_toll_manufacturing/models/batch_toll_manufacturing_order.py
odoo/addons/ssi_toll_manufacturing/models/stock_move.py
odoo/addons/ssi_toll_manufacturing/models/stock_rule.py
odoo/addons/ssi_toll_manufacturing/models/toll_manufacturing_acceptance.py
odoo/addons/ssi_toll_manufacturing/models/toll_manufacturing_acceptance_customer_supplied_raw_material.py
odoo/addons/ssi_toll_manufacturing/models/toll_manufacturing_acceptance_processing_fee.py
odoo/addons/ssi_toll_manufacturing/models/toll_manufacturing_acceptance_supplier_procured_raw_material.py
odoo/addons/ssi_toll_manufacturing/models/toll_manufacturing_order.py
odoo/addons/ssi_toll_manufacturing/models/toll_manufacturing_order_bom.py
odoo14_addon_ssi_toll_manufacturing-14.0.1.0.1.dev6.dist-info/METADATA
odoo14_addon_ssi_toll_manufacturing-14.0.1.0.1.dev6.dist-info/WHEEL
odoo14_addon_ssi_toll_manufacturing-14.0.1.0.1.dev6.dist-info/top_level.txt
odoo14_addon_ssi_toll_manufacturing-14.0.1.0.1.dev6.dist-info/RECORD
